MANIFEST.in
README.rst
rfc2397.py
setup.py
rfc2397.egg-info/PKG-INFO
rfc2397.egg-info/SOURCES.txt
rfc2397.egg-info/dependency_links.txt
rfc2397.egg-info/entry_points.txt
rfc2397.egg-info/top_level.txt