Metadata-Version: 1.0
Name: rfc2397
Version: 1.0b2
Summary: A Python RFC2397 implementation
Home-page: UNKNOWN
Author: Jacob Oscarson
Author-email: jacob@plexical.com
License: MIT
Platform: UNKNOWN
Classifier: Development Status :: 4 - Beta
Classifier: License :: OSI Approved :: MIT License
Classifier: Operating System :: OS Independent
Classifier: Programming Language :: Python
Classifier: Environment :: Console
Classifier: Topic :: Internet :: WWW/HTTP :: Site Management
Classifier: Topic :: Multimedia :: Graphics :: Graphics Conversion
